MANIFEST.in
README
distribute_setup.py
setup.py
django_repositories.egg-info/PKG-INFO
django_repositories.egg-info/SOURCES.txt
django_repositories.egg-info/dependency_links.txt
django_repositories.egg-info/top_level.txt
repositories/__init__.py
repositories/admin.py
repositories/forms.py
repositories/models.py
repositories/settings.py
repositories/signals.py
repositories/tests.py
repositories/urls.py
repositories/utils.py
repositories/vcs.py
repositories/views.py
repositories/bin/auth.wsgi
repositories/bin/initialize_git_repo.sh
repositories/management/__init__.py
repositories/management/commands/__init__.py
repositories/management/commands/repo_check_for_updates.py
repositories/management/commands/repo_export.py
repositories/management/commands/repo_generate_apache_conf.py
repositories/management/commands/repo_generate_auth.py
repositories/templates/repositories/apache2_auth.conf
repositories/templates/repositories/apache2_bazaar.conf
repositories/templates/repositories/apache2_git.conf
repositories/templates/repositories/apache2_mercurial.conf
repositories/templates/repositories/apache2_subversion.conf
repositories/templates/repositories/hooks/post-update