Metadata-Version: 1.0
Name: django-repositories
Version: 0.1.1
Summary: Version Control system management
Home-page: http://opensource.washingtontimes.com/projects/django-repositories/
Author: Corey Oordt
Author-email: coordt@washingtontimes.com
License: Apache Software License
Platform: UNKNOWN
Classifier: Development Status :: 3 - Alpha
Classifier: Framework :: Django
Classifier: License :: OSI Approved :: Apache Software License
Classifier: Intended Audience :: Developers
Classifier: Topic :: Software Development
